LICENSE
MANIFEST.in
README.md
package.json
setup.py
new_test_new_new/NewTestNewNew.py
new_test_new_new/__init__.py
new_test_new_new/_imports_.py
new_test_new_new/async-NewTestNewNew.js
new_test_new_new/async-NewTestNewNew.js.map
new_test_new_new/metadata.json
new_test_new_new/new_test_new_new.min.js
new_test_new_new/new_test_new_new.min.js.map
new_test_new_new/package-info.json
new_test_new_new.egg-info/PKG-INFO
new_test_new_new.egg-info/SOURCES.txt
new_test_new_new.egg-info/dependency_links.txt
new_test_new_new.egg-info/top_level.txt