Metadata-Version: 2.1
Name: new-test-new-new
Version: 0.0.3
Summary: Enjoy the dash spinner for your Python Dash component
Home-page: UNKNOWN
Author: chiranjeevi <chiranjeevi.exf@gmail.com>
License: MIT
Platform: UNKNOWN
Classifier: Framework :: Dash
Classifier: Programming Language :: Python :: 3.7
Classifier: Programming Language :: Python :: 3.8
Classifier: Programming Language :: Python :: 3.9
Classifier: Programming Language :: Python :: 3.10
